main.py
weather_buding888-0.1.0.dist-info/METADATA
weather_buding888-0.1.0.dist-info/WHEEL
weather_buding888-0.1.0.dist-info/top_level.txt
weather_buding888-0.1.0.dist-info/RECORD
