Metadata-Version: 2.4
Name: weather-buding888
Version: 0.1.0
Summary: Add your description here
Requires-Python: >=3.11
Requires-Dist: httpx>=0.28.1
Requires-Dist: mcp>=1.21.0
Requires-Dist: requests>=2.32.5
